{
  "name": "mitigation_cb-2070",
  "data": [
    {
      "seriesName": "FT_AGR",
      "seriesValues": [
        [
          2018,
          8.72328069738806
        ],
        [
          2019,
          8.72332472300702
        ],
        [
          2020,
          8.68360468873377
        ],
        [
          2021,
          8.66676158125713
        ],
        [
          2022,
          10.4971899209848
        ],
        [
          2023,
          10.4459505741675
        ],
        [
          2024,
          10.324412988783
        ],
        [
          2025,
          10.4078780097279
        ],
        [
          2026,
          10.5500705385051
        ],
        [
          2027,
          10.5454212523574
        ],
        [
          2028,
          10.5958508856471
        ],
        [
          2029,
          10.5405707050542
        ],
        [
          2030,
          10.5421205535144
        ],
        [
          2031,
          9.07401022704652
        ],
        [
          2032,
          9.09998344688902
        ],
        [
          2035,
          4.19575825365686
        ],
        [
          2040,
          6.25256474932698
        ],
        [
          2045,
          9.19695048917045
        ],
        [
          2050,
          9.15179892075161
        ]
      ]
    },
    {
      "seriesName": "FT_IND",
      "seriesValues": [
        [
          2018,
          4.21855231669348
        ],
        [
          2019,
          4.18021811875085
        ],
        [
          2020,
          4.16874990907663
        ],
        [
          2021,
          4.16476183669322
        ],
        [
          2022,
          4.75476866779929
        ],
        [
          2023,
          4.63562892853301
        ],
        [
          2024,
          4.51695592355931
        ],
        [
          2025,
          4.3983630674616
        ],
        [
          2026,
          4.27946256593537
        ],
        [
          2027,
          5.21629027598793
        ],
        [
          2028,
          5.2474292511333
        ],
        [
          2029,
          5.28044744034895
        ],
        [
          2030,
          5.31538439876852
        ],
        [
          2031,
          3.55928302024623
        ],
        [
          2032,
          3.39981077819298
        ],
        [
          2035,
          2.90870204773485
        ],
        [
          2040,
          2.03516382145347
        ],
        [
          2045,
          1.07453239592215
        ],
        [
          2050,
          1.20796964401252e-06
        ]
      ]
    },
    {
      "seriesName": "FT_SRV",
      "seriesValues": [
        [
          2018,
          4.47455876400002
        ],
        [
          2019,
          3.93763552418428
        ],
        [
          2020,
          4.2668817820856
        ],
        [
          2021,
          4.07809608870128
        ],
        [
          2022,
          0.817985331331392
        ],
        [
          2023,
          0.76686124812318
        ],
        [
          2024,
          0.715737164914968
        ],
        [
          2025,
          0.664613081706756
        ],
        [
          2026,
          0.613488998498544
        ],
        [
          2027,
          0.19238593266347
        ],
        [
          2028,
          0.51124083208212
        ],
        [
          2029,
          0.460116748873908
        ],
        [
          2030,
          0.408992665665696
        ],
        [
          2031,
          0.357868582457484
        ],
        [
          2032,
          0.306744499249272
        ],
        [
          2035,
          0.0375145401225982
        ]
      ]
    },
    {
      "seriesName": "FT_TRA",
      "seriesValues": [
        [
          2018,
          128.908352563338
        ],
        [
          2019,
          130.9
        ],
        [
          2020,
          113.2
        ],
        [
          2021,
          121.1
        ],
        [
          2022,
          137.73630669692
        ],
        [
          2023,
          141.324191488702
        ],
        [
          2024,
          142.40872172871
        ],
        [
          2025,
          139.675380859577
        ],
        [
          2026,
          114.925731793799
        ],
        [
          2027,
          96.8220728921824
        ],
        [
          2028,
          79.0995561203708
        ],
        [
          2029,
          76.8042460037138
        ],
        [
          2030,
          77.0029624371977
        ],
        [
          2031,
          75.6252813952379
        ],
        [
          2032,
          67.4850688219714
        ],
        [
          2035,
          31.6284019177243
        ],
        [
          2040,
          10.3063017253833
        ],
        [
          2045,
          7.70270883263906
        ],
        [
          2050,
          7.72262492492969
        ]
      ]
    }
  ]
}