{
  "name": "mitigation_cb-2070",
  "data": [
    {
      "seriesName": "FT_AGR",
      "seriesValues": [
        [
          2018,
          2.0294956157424715
        ],
        [
          2019,
          1.9999999999999998
        ],
        [
          2020,
          2.0080718920229845
        ],
        [
          2021,
          1.9981026672130568
        ],
        [
          2031,
          2.0287918294577136
        ],
        [
          2032,
          2.028300231166322
        ],
        [
          2045,
          1.7482176689836209
        ],
        [
          2050,
          1.7118702168738011
        ]
      ]
    },
    {
      "seriesName": "FT_IND",
      "seriesValues": [
        [
          2018,
          23.54587003726455
        ],
        [
          2019,
          24.003147136233018
        ],
        [
          2020,
          22.34539186975353
        ],
        [
          2021,
          22.337206784206895
        ],
        [
          2022,
          25.145441884251934
        ],
        [
          2023,
          25.631740184932845
        ],
        [
          2024,
          26.12454938253801
        ],
        [
          2025,
          26.62452804793644
        ],
        [
          2026,
          27.132428729301505
        ],
        [
          2027,
          27.529739956575053
        ],
        [
          2028,
          27.929421592780457
        ],
        [
          2029,
          28.334620383058883
        ],
        [
          2030,
          28.745422073300844
        ],
        [
          2031,
          29.160125450321527
        ],
        [
          2032,
          29.610254298982774
        ],
        [
          2035,
          31.001803407406534
        ],
        [
          2040,
          33.44523582301327
        ],
        [
          2045,
          36.055373135242995
        ],
        [
          2050,
          38.861133177754226
        ]
      ]
    },
    {
      "seriesName": "FT_RSD",
      "seriesValues": [
        [
          2018,
          30.6814593518889
        ],
        [
          2019,
          30.800000000000008
        ],
        [
          2020,
          31.499999999999996
        ],
        [
          2021,
          31.500000000000014
        ],
        [
          2022,
          32.82861002484645
        ],
        [
          2023,
          33.10930349219906
        ],
        [
          2024,
          33.105255485047756
        ],
        [
          2025,
          33.09848227648525
        ],
        [
          2026,
          32.36459462774571
        ],
        [
          2027,
          32.28265392405332
        ],
        [
          2028,
          31.017792269958626
        ],
        [
          2029,
          30.826366228048716
        ],
        [
          2030,
          30.68710186117538
        ],
        [
          2031,
          34.24779316359696
        ],
        [
          2032,
          35.626978734998865
        ],
        [
          2035,
          35.030278008398206
        ],
        [
          2040,
          39.82719425034983
        ],
        [
          2045,
          50.01805467562186
        ],
        [
          2050,
          56.29073939003217
        ]
      ]
    },
    {
      "seriesName": "FT_SRV",
      "seriesValues": [
        [
          2018,
          45.18307247976257
        ],
        [
          2019,
          46.9
        ],
        [
          2020,
          47.100000000000016
        ],
        [
          2021,
          49.90000000000002
        ],
        [
          2022,
          59.98023477626043
        ],
        [
          2023,
          61.022980249633
        ],
        [
          2024,
          64.82893942217657
        ],
        [
          2025,
          66.94483025237577
        ],
        [
          2026,
          69.66353232123392
        ],
        [
          2027,
          73.86845983754893
        ],
        [
          2028,
          81.23472612810475
        ],
        [
          2029,
          89.85861032221416
        ],
        [
          2030,
          94.05817567626238
        ],
        [
          2031,
          92.44959772466446
        ],
        [
          2032,
          96.17442399157218
        ],
        [
          2035,
          94.58477181338343
        ],
        [
          2040,
          95.80664957396169
        ],
        [
          2045,
          97.41856039056863
        ],
        [
          2050,
          97.20148034205485
        ]
      ]
    },
    {
      "seriesName": "FT_TRA",
      "seriesValues": [
        [
          2018,
          0.3829999999999988
        ],
        [
          2019,
          0.2999999999999976
        ],
        [
          2020,
          0.2999999999999976
        ],
        [
          2021,
          0.4999999999999985
        ],
        [
          2022,
          0.3919852077651259
        ],
        [
          2023,
          0.3967982287555171
        ],
        [
          2024,
          0.6121771474787717
        ],
        [
          2025,
          1.3886766866024605
        ],
        [
          2026,
          4.144287945513212
        ],
        [
          2027,
          8.826715613337578
        ],
        [
          2028,
          13.653751876813718
        ],
        [
          2029,
          14.948460595776265
        ],
        [
          2030,
          15.907690097633154
        ],
        [
          2031,
          17.992276383585356
        ],
        [
          2032,
          22.191207764316136
        ],
        [
          2035,
          47.25747232618212
        ],
        [
          2040,
          69.29164011315136
        ],
        [
          2045,
          78.91889589862633
        ],
        [
          2050,
          86.32604318461395
        ]
      ]
    }
  ]
}